MANIFEST.in
README.rst
setup.py
docs/HISTORY.txt
docs/LICENSE.GPL
docs/LICENSE.txt
ftw/__init__.py
ftw.tooltip.egg-info/PKG-INFO
ftw.tooltip.egg-info/SOURCES.txt
ftw.tooltip.egg-info/dependency_links.txt
ftw.tooltip.egg-info/entry_points.txt
ftw.tooltip.egg-info/namespace_packages.txt
ftw.tooltip.egg-info/not-zip-safe
ftw.tooltip.egg-info/requires.txt
ftw.tooltip.egg-info/top_level.txt
ftw/tooltip/__init__.py
ftw/tooltip/configure.zcml
ftw/tooltip/demo_tooltip_source.py
ftw/tooltip/interfaces.py
ftw/tooltip/testing.py
ftw/tooltip/Extensions/install.py
ftw/tooltip/browser/__init__.py
ftw/tooltip/browser/configure.zcml
ftw/tooltip/browser/ftw_tooltip.css
ftw/tooltip/browser/tooltip.py
ftw/tooltip/browser/tooltip_template.js.pt
ftw/tooltip/locales/ftw.tooltip.pot
ftw/tooltip/locales/de/LC_MESSAGES/ftw.tooltip.po
ftw/tooltip/profiles/default/cssregistry.xml
ftw/tooltip/profiles/default/jsregistry.xml
ftw/tooltip/profiles/default/metadata.xml
ftw/tooltip/profiles/uninstall/cssregistry.xml
ftw/tooltip/profiles/uninstall/jsregistry.xml
ftw/tooltip/tests/__init__.py
ftw/tooltip/tests/test_tooltip.py
ftw/tooltip/tests/test_uninstall.py
ftw/tooltip/tests/tests.zcml
ftw/tooltip/upgrades/__init__.py
ftw/tooltip/upgrades/configure.zcml
ftw/tooltip/upgrades/profiles/1131/jsregistry.xml
ftw/tooltip/upgrades/profiles/1132/jsregistry.xml