Metadata-Version: 2.1
Name: ftw.tooltip
Version: 2.0.0
Summary: Apply tooltips dynamically
Home-page: https://github.com/4teamwork/ftw.tooltip
Author: 4teamwork AG
Author-email: mailto:info@4teamwork.ch
License: GPL2
Platform: UNKNOWN
Classifier: Framework :: Plone
Classifier: Framework :: Plone :: 4.3
Classifier: License :: OSI Approved :: GNU General Public License (GPL)
Classifier: Programming Language :: Python
Classifier: Topic :: Software Development :: Libraries :: Python Modules
Provides-Extra: tests
